{
	"apiVersion": 2,
	"name": "ramp/article-teasers",
	"title": "Article Teasers",
	"icon": "lightbulb",
	"category": "ramp",
	"style": "file:../../../../build/index.css",
	"supports": {
		"anchor": true
	},
	"attributes": {
		"featuredItemId": {
			"type": "number",
			"default": 0
		},
		"isEditMode": {
			"type": "boolean",
			"default": false
		},
		"researchTopic": {
			"type": "string",
			"default": "auto"
		},
		"showFeaturedItem": {
			"type": "boolean",
			"default": "false"
		},
		"variationType": {
			"enum": [ "grid", "columns" ],
			"default": "grid"
		}
	}
}
